slackeventsapi/__init__.py
slackeventsapi/server.py
slackeventsapi/version.py
slackeventsapi-3.0.3.dist-info/LICENSE
slackeventsapi-3.0.3.dist-info/METADATA
slackeventsapi-3.0.3.dist-info/WHEEL
slackeventsapi-3.0.3.dist-info/top_level.txt
slackeventsapi-3.0.3.dist-info/RECORD
